[
  {
    "source": "zjt",
    "title": "关于面向全社会 公开征集自治区住房和城乡建设行业高质量发展“十五五”规划意见建议的公告",
    "url": "https://zjt.xinjiang.gov.cn/xjzjt/c113382/202509/67542140a688471cbf481451902003da.shtml",
    "date": "2025-09-05",
    "categories": []
  },
  {
    "source": "zjt",
    "title": "关于发布《自治区城市公园名录》的公告",
    "url": "https://zjt.xinjiang.gov.cn/xjzjt/c113382/202606/384e033004504eb1a3a8b14a34875bd8.shtml",
    "date": "2026-06-23",
    "categories": []
  },
  {
    "source": "zjt",
    "title": "关于发布自治区住房城乡建设厅权责清单（2025版）的公告",
    "url": "https://zjt.xinjiang.gov.cn/xjzjt/c113382/202606/1a1b285d7474470096f80eba5e5e84a0.shtml",
    "date": "2026-06-22",
    "categories": []
  },
  {
    "source": "zjt",
    "title": "关于发布自治区“治理物业服务突出问题”第五批违法违规典型案例的公告",
    "url": "https://zjt.xinjiang.gov.cn/xjzjt/c113382/202606/4d42fc60c4584d369f6bb3faba4817a1.shtml",
    "date": "2026-06-22",
    "categories": []
  },
  {
    "source": "zjt",
    "title": "关于规范自治区住房城乡建设领域信用评价工作的通知",
    "url": "https://zjt.xinjiang.gov.cn/xjzjt/c113382/202606/00a00dcd8ce64a4ebbe3930add314afd.shtml",
    "date": "2026-06-16",
    "categories": []
  },
  {
    "source": "zjt",
    "title": "关于2026年第四批《新疆维吾尔自治区新型墙体材料认定证书》的公示",
    "url": "https://zjt.xinjiang.gov.cn/xjzjt/c113382/202606/5ff11bf2f027414787222ce7f5bf0c01.shtml",
    "date": "2026-06-11",
    "categories": []
  },
  {
    "source": "zjt",
    "title": "关于开展2026年度自治区建设工程质量安全监督人员、工程项目责任主体、质量检测机构及预拌混凝土企业质量安全管理人员培训工作的通知",
    "url": "https://zjt.xinjiang.gov.cn/xjzjt/c113382/202606/c2ad7eb18c334b7fbcafb77ef659ee2b.shtml",
    "date": "2026-06-08",
    "categories": []
  },
  {
    "source": "zjt",
    "title": "关于2026年第一批《新疆维吾尔自治区新型墙体材料认定证书》变更法人的公示",
    "url": "https://zjt.xinjiang.gov.cn/xjzjt/c113382/202606/9b58c12145254e31bb1a1c5f5172b7db.shtml",
    "date": "2026-06-01",
    "categories": []
  },
  {
    "source": "zjt",
    "title": "关于发布自治区城市公园建设（改造）典型案例的公告",
    "url": "https://zjt.xinjiang.gov.cn/xjzjt/c113382/202606/0f8e719e914446368c60ed6bedc0dd09.shtml",
    "date": "2026-05-18",
    "categories": []
  },
  {
    "source": "zjt",
    "title": "关于印发《自治区城镇住宅工程质量易发问题专项整治暨品质提升三年行动方案(2026—2028年)》的通知",
    "url": "https://zjt.xinjiang.gov.cn/xjzjt/c113382/202605/39108baf9b194462af01174e4bf76588.shtml",
    "date": "2026-05-18",
    "categories": []
  },
  {
    "source": "zjt",
    "title": "关于对部分建筑业企业不满足资质标准限期整改的通知",
    "url": "https://zjt.xinjiang.gov.cn/xjzjt/c113382/202605/f6b3926a8bde4de3bffd4f9a5fc975c4.shtml",
    "date": "2026-05-14",
    "categories": []
  },
  {
    "source": "zjt",
    "title": "关于进一步推进自治区建筑信息模型（BIM）技术全生命周期应用的通知",
    "url": "https://zjt.xinjiang.gov.cn/xjzjt/c113382/202605/1c73f0afa8ad4725984ece400f6465cb.shtml",
    "date": "2026-05-08",
    "categories": []
  },
  {
    "source": "zjt",
    "title": "关于发布新疆维吾尔自治区智能建造（建筑机器人）消耗量定额项目（试行）的通知",
    "url": "https://zjt.xinjiang.gov.cn/xjzjt/c113382/202605/a960625a6b4049d8ba71073bc72132d7.shtml",
    "date": "2026-05-07",
    "categories": [
      "定额",
      "智能建造"
    ]
  },
  {
    "source": "zjt",
    "title": "关于2025年度建设工程质量检测机构和预拌混凝土生产企业信用评价结果的公示",
    "url": "https://zjt.xinjiang.gov.cn/xjzjt/c113382/202605/af2516da6852418eaabd89e28bbf3fe0.shtml",
    "date": "2026-05-06",
    "categories": []
  },
  {
    "source": "zjt",
    "title": "关于2026年第三批《新疆维吾尔自治区新型墙体材料认定证书》的公示",
    "url": "https://zjt.xinjiang.gov.cn/xjzjt/c113382/202604/773a319209ab42468b659a78b524ba66.shtml",
    "date": "2026-04-29",
    "categories": []
  },
  {
    "source": "zjt",
    "title": "关于贯彻执行《建设工程工程量清单计价标准》（GB/T50500-2024）及各专业工程工程量计算标准的通知",
    "url": "https://zjt.xinjiang.gov.cn/xjzjt/c113382/202604/037dfa27dfc04269a1e1d791476c72ab.shtml",
    "date": "2026-04-29",
    "categories": [
      "国标"
    ]
  },
  {
    "source": "zjt",
    "title": "关于进一步加强房屋建筑和市政基础设施工程项目实名制管理工作的通知",
    "url": "https://zjt.xinjiang.gov.cn/xjzjt/c113382/202604/bbb8a98444694818bbdf3580beff15b1.shtml",
    "date": "2026-04-24",
    "categories": []
  },
  {
    "source": "zjt",
    "title": "关于印发2026年“消防审验·云讲堂”课程安排的通知",
    "url": "https://zjt.xinjiang.gov.cn/xjzjt/c113382/202604/020aab5aad4f4111a24d6804fe0cba10.shtml",
    "date": "2026-04-23",
    "categories": []
  },
  {
    "source": "zjt",
    "title": "关于发布自治区“治理物业服务突出问题”第四批违法违规典型案例的公告",
    "url": "https://zjt.xinjiang.gov.cn/xjzjt/c113382/202604/8d124a09ddf6406c833efb1f3be4a5ae.shtml",
    "date": "2026-04-22",
    "categories": []
  },
  {
    "source": "zjt",
    "title": "自治区住房城乡建设厅、自治区国防动员办公室关于调整修订《自治区高效办成建设项目联合验收“一件事”业务工作方案》部分内容的通知",
    "url": "https://zjt.xinjiang.gov.cn/xjzjt/c113382/202604/fc68cd0d93784ef39d2a61674063a6de.shtml",
    "date": "2026-04-20",
    "categories": [
      "勘误"
    ]
  },
  {
    "source": "zjt",
    "title": "关于进一步规范自治区建设工程抗震管理有关工作的通知",
    "url": "https://zjt.xinjiang.gov.cn/xjzjt/c113382/202604/befe87a0645b433cb113d670c2c51e57.shtml",
    "date": "2026-04-20",
    "categories": []
  },
  {
    "source": "zjt",
    "title": "新疆维吾尔自治区房屋建筑和市政基础设施工程招标投标领域违法违规典型案例通报（2026年第一批）",
    "url": "https://zjt.xinjiang.gov.cn/xjzjt/c113382/202604/18b2173552434f529fd11190b2873132.shtml",
    "date": "2026-04-17",
    "categories": []
  },
  {
    "source": "zjt",
    "title": "自治区住房城乡建设厅选聘法律顾问单位公告",
    "url": "https://zjt.xinjiang.gov.cn/xjzjt/c113382/202604/00130cf8de5a47e4bb443b6e61b38c70.shtml",
    "date": "2026-04-16",
    "categories": []
  },
  {
    "source": "zjt",
    "title": "关于自治区建设工程质量检测机构资质评审、预拌混凝土、体育设施建设、质量安全监督专家库的公示",
    "url": "https://zjt.xinjiang.gov.cn/xjzjt/c113382/202604/3975115c82ab46afb4ef577c162753c6.shtml",
    "date": "2026-04-09",
    "categories": []
  },
  {
    "source": "zjt",
    "title": "关于2026年第二批《新疆维吾尔自治区新型墙体材料认定证书》的公示",
    "url": "https://zjt.xinjiang.gov.cn/xjzjt/c113382/202604/fa5e38b955034575835055ba518fe121.shtml",
    "date": "2026-04-03",
    "categories": []
  },
  {
    "source": "zjt",
    "title": "新疆维吾尔自治区农村危房改造中央专项转移支付2025年度绩效自评报告",
    "url": "https://zjt.xinjiang.gov.cn/xjzjt/c113382/202603/06d2da65121d43a199e9d8679e221e99.shtml",
    "date": "2026-03-30",
    "categories": []
  },
  {
    "source": "zjt",
    "title": "关于发布新疆维吾尔自治区物业主管部门咨询投诉电话和自治区物业服务企业服务行为负面清单2.0的公告",
    "url": "https://zjt.xinjiang.gov.cn/xjzjt/c113382/202603/d072495fd9a740139da0db5bd51a233e.shtml",
    "date": "2026-03-27",
    "categories": []
  },
  {
    "source": "zjt",
    "title": "关于2025年度自治区工程建设标准复审意见的公示",
    "url": "https://zjt.xinjiang.gov.cn/xjzjt/c113382/202603/d19432b3a1b244c7aecf1400de38ce19.shtml",
    "date": "2026-03-02",
    "categories": []
  },
  {
    "source": "zjt",
    "title": "关于2025年监理企业信用评价结果的公告",
    "url": "https://zjt.xinjiang.gov.cn/xjzjt/c113382/202602/e858e2c0cd7a4ffd9bcfadae46b95adc.shtml",
    "date": "2026-02-27",
    "categories": []
  },
  {
    "source": "zjt",
    "title": "关于开展工程建设项目招标代理机构信息登记工作的通知",
    "url": "https://zjt.xinjiang.gov.cn/xjzjt/c113382/202602/a34e575bc53d45aca2904a4b27b993cb.shtml",
    "date": "2026-02-26",
    "categories": []
  },
  {
    "source": "zjt",
    "title": "关于对2025年施工图审查机构及从业人员信用评价结果的公告",
    "url": "https://zjt.xinjiang.gov.cn/xjzjt/c113382/202602/57475ef4342e4dce9343beadf4ea511a.shtml",
    "date": "2026-02-14",
    "categories": []
  },
  {
    "source": "zjt",
    "title": "公告┃自治区住房和城乡建设厅2026年公开招录公务员2名、公开遴选公务员1名",
    "url": "https://zjt.xinjiang.gov.cn/xjzjt/c113382/202602/a5945d753c1c4e1294ef0f8836e49bf0.shtml",
    "date": "2026-02-04",
    "categories": []
  },
  {
    "source": "zjt",
    "title": "自治区“整治物业服务履约不到位、侵占业主公共收益等问题”典型案例通报（第三批）",
    "url": "https://zjt.xinjiang.gov.cn/xjzjt/c113382/202602/c808e67f612843708a16e6d977255176.shtml",
    "date": "2026-01-31",
    "categories": []
  },
  {
    "source": "zjt",
    "title": "关于2026年第一批新疆维吾尔自治区新型墙体材料认定证书的公示",
    "url": "https://zjt.xinjiang.gov.cn/xjzjt/c113382/202601/66518ae8ff7040e1bd220481244afbe1.shtml",
    "date": "2026-01-30",
    "categories": []
  },
  {
    "source": "zjt",
    "title": "关于公布2025年房屋市政工程安全生产标准化建设优质项目名单的公告",
    "url": "https://zjt.xinjiang.gov.cn/xjzjt/c113382/202602/cde2ae040e6149fb807b3c768c6142c7.shtml",
    "date": "2026-01-27",
    "categories": []
  },
  {
    "source": "zjt",
    "title": "关于开展2025年度招标代理机构信用评价工作的通知",
    "url": "https://zjt.xinjiang.gov.cn/xjzjt/c113382/202601/c13aa3bc6a6d4a25aa22ea14897754e7.shtml",
    "date": "2026-01-13",
    "categories": []
  },
  {
    "source": "zjt",
    "title": "关于面向全社会公开征求《新疆维吾尔自治区建设工程造价管理办法（征求意见稿）》意见建议的公示",
    "url": "https://zjt.xinjiang.gov.cn/xjzjt/c113382/202601/900c24501d304e4aa22631aafc9d3d83.shtml",
    "date": "2026-01-13",
    "categories": [
      "造价管理办法"
    ]
  },
  {
    "source": "zjt",
    "title": "关于公开征求拟新增建设工程质量检测资质可选检测项目及参数意见建议的公示",
    "url": "https://zjt.xinjiang.gov.cn/xjzjt/c113382/202601/cc762b471b424c27ad706d1719b51cbb.shtml",
    "date": "2026-01-07",
    "categories": []
  },
  {
    "source": "zjt",
    "title": "关于2025年上半年自治区勘察设计企业及从业注册人员信用评价结果的公示",
    "url": "https://zjt.xinjiang.gov.cn/xjzjt/c113382/202601/655be4d05c5544c2a7902313fdd46d11.shtml",
    "date": "2026-01-05",
    "categories": []
  },
  {
    "source": "zjt",
    "title": "2025年度“新疆市政工程协会市政工程最高质量水平评价活动”评选结果公示",
    "url": "https://zjt.xinjiang.gov.cn/xjzjt/c113382/202512/01e47b30af9f4c3e80b0d82368f0425c.shtml",
    "date": "2025-12-31",
    "categories": []
  },
  {
    "source": "zjt",
    "title": "自治区“整治物业服务履约不到位、侵占业主公共收益等问题”典型案例（第二批）",
    "url": "https://zjt.xinjiang.gov.cn/xjzjt/c113382/202512/07a912b2b02c416fa8f491eabdc70d1e.shtml",
    "date": "2025-12-26",
    "categories": []
  },
  {
    "source": "zjt",
    "title": "关于更新补充自治区建设工程质量检测机构资质评审、预拌混凝土、体育设施建设行业专家库的通知",
    "url": "https://zjt.xinjiang.gov.cn/xjzjt/c113382/202512/a6ceec734f2d4406867f29aa31d433ff.shtml",
    "date": "2025-12-24",
    "categories": []
  },
  {
    "source": "zjt",
    "title": "关于规范和强化物业服务企业履行“劝阻、制止、报告”职责的通知",
    "url": "https://zjt.xinjiang.gov.cn/xjzjt/c113382/202512/2e0d3572c18a43dbb6b5e19f187086d1.shtml",
    "date": "2025-12-24",
    "categories": []
  },
  {
    "source": "zjt",
    "title": "2025年全区第一批房建和市政工程评标专家拟入库及继续教育合格名单公示",
    "url": "https://zjt.xinjiang.gov.cn/xjzjt/c113382/202512/b17a9709b7494c0f8b25487591c6fef7.shtml",
    "date": "2025-12-09",
    "categories": []
  },
  {
    "source": "zjt",
    "title": "关于2025年第九批《新疆维吾尔自治区新型墙体材料认定证书》的公示",
    "url": "https://zjt.xinjiang.gov.cn/xjzjt/c113382/202512/3044d8fd50404eda9bd6bc7fd2bcba41.shtml",
    "date": "2025-12-08",
    "categories": []
  },
  {
    "source": "zjt",
    "title": "关于开展2025年度自治区物业服务企业信用评价工作的通知",
    "url": "https://zjt.xinjiang.gov.cn/xjzjt/c113382/202512/179733400da94724a009cbd56ad54ff4.shtml",
    "date": "2025-12-01",
    "categories": []
  },
  {
    "source": "zjt",
    "title": "关于印发《自治区高效办成建设项目联合验收“一件事”业务工作方案》的通知",
    "url": "https://zjt.xinjiang.gov.cn/xjzjt/c113382/202511/57e2e76318a54dae8f518042679c548f.shtml",
    "date": "2025-11-27",
    "categories": []
  },
  {
    "source": "zjt",
    "title": "自治区公布房地产领域信用评价结果",
    "url": "https://zjt.xinjiang.gov.cn/xjzjt/c113382/202511/efb755e68e2949e0b978c74f2567fa0e.shtml",
    "date": "2025-11-20",
    "categories": []
  },
  {
    "source": "zjt",
    "title": "关于开展2025年度工程造价咨询企业及执业从业人员信用评价工作的通知",
    "url": "https://zjt.xinjiang.gov.cn/xjzjt/c113382/202512/7f405bfb8cde4f6bb184e49aee316561.shtml",
    "date": "2025-11-18",
    "categories": []
  },
  {
    "source": "zjt",
    "title": "新疆维吾尔自治区建设工程招标投标服务中心拟申请注销登记的公告",
    "url": "https://zjt.xinjiang.gov.cn/xjzjt/c113382/202512/48568f44070843e5ba86bf8a4e3d5f9f.shtml",
    "date": "2025-11-15",
    "categories": []
  },
  {
    "source": "zjt",
    "title": "新疆维吾尔自治区工程造价总站拟申请注销登记的公告",
    "url": "https://zjt.xinjiang.gov.cn/xjzjt/c113382/202512/06cbe375a1ce45b0a49835b66b82c751.shtml",
    "date": "2025-11-15",
    "categories": []
  },
  {
    "source": "zjt",
    "title": "新疆维吾尔自治区建设标准服务中心拟申请注销登记的公告",
    "url": "https://zjt.xinjiang.gov.cn/xjzjt/c113382/202512/77a91ed1d3c942d5a0110a45f5f3844e.shtml",
    "date": "2025-11-15",
    "categories": []
  },
  {
    "source": "zjt",
    "title": "关于修改自治区房屋建筑和市政基础设施项目施工招标文件示范文本等文件的通知",
    "url": "https://zjt.xinjiang.gov.cn/xjzjt/c113382/202601/30c8cdcfac4e486ab4c6517d376db1a8.shtml",
    "date": "2025-11-13",
    "categories": []
  },
  {
    "source": "zjt",
    "title": "关于对2025年第二次施工企业信用评价结果的公告",
    "url": "https://zjt.xinjiang.gov.cn/xjzjt/c113382/202511/6302c4a922dd4815bfd2feb69a8a0406.shtml",
    "date": "2025-11-11",
    "categories": []
  },
  {
    "source": "zjt",
    "title": "关于发布新疆维吾尔自治区2025年度住房城乡建设领域“揭榜挂帅”项目榜单的通知",
    "url": "https://zjt.xinjiang.gov.cn/xjzjt/c113382/202511/0d296cc928ef432a88300924045e8096.shtml",
    "date": "2025-11-05",
    "categories": []
  },
  {
    "source": "zjt",
    "title": "关于进一步明确建筑垃圾运输及处置计价工作的通知",
    "url": "https://zjt.xinjiang.gov.cn/xjzjt/c113382/202511/b2d73749820540deb6ed09dc311a8016.shtml",
    "date": "2025-11-04",
    "categories": []
  },
  {
    "source": "zjt",
    "title": "关于监理企业信用评价结果的公示",
    "url": "https://zjt.xinjiang.gov.cn/xjzjt/c113382/202511/f32394d7c4ad4c02bfd78e832245fbb7.shtml",
    "date": "2025-11-04",
    "categories": []
  },
  {
    "source": "zjt",
    "title": "关于2024年度自治区房地产开发企业物业服务企业、房地产经纪机构房地产估价机构和相关从业人员信用评价结果的公告",
    "url": "https://zjt.xinjiang.gov.cn/xjzjt/c113382/202511/411936df04ad4f0e88b61c29628e7fb7.shtml",
    "date": "2025-10-29",
    "categories": []
  },
  {
    "source": "zjt",
    "title": "关于拟提名申报2025年度自治区科学技术奖项目的公示",
    "url": "https://zjt.xinjiang.gov.cn/xjzjt/c113382/202510/a7c506e2d4664d1a950a59876db4edf8.shtml",
    "date": "2025-10-28",
    "categories": []
  },
  {
    "source": "zjt",
    "title": "关于2025年第一批《新疆维吾尔自治区新型墙体材料认定证书》变更法人的公示",
    "url": "https://zjt.xinjiang.gov.cn/xjzjt/c113382/202510/93d683a5e6d544c48fc0650f4f7db831.shtml",
    "date": "2025-10-26",
    "categories": []
  },
  {
    "source": "zjt",
    "title": "关于成立自治区住房城乡建设厅建筑风貌设计专家委员会的通知",
    "url": "https://zjt.xinjiang.gov.cn/xjzjt/c113382/202510/3c047a0a125b4777be4ac1774ead09cf.shtml",
    "date": "2025-10-23",
    "categories": []
  },
  {
    "source": "zjt",
    "title": "关于申报2026年度自治区工程建设标准制修订项目计划的通知",
    "url": "https://zjt.xinjiang.gov.cn/xjzjt/c113382/202510/c46aa6a26e5e4318887be2b5a332ee10.shtml",
    "date": "2025-10-15",
    "categories": []
  },
  {
    "source": "zjt",
    "title": "新疆维吾尔自治区建设标准服务中心拟申请注销登记的公告",
    "url": "https://zjt.xinjiang.gov.cn/xjzjt/c113382/202511/275975368dd24738afadb9116474653d.shtml",
    "date": "2025-10-15",
    "categories": []
  },
  {
    "source": "zjt",
    "title": "新疆维吾尔自治区工程造价总站拟申请注销登记的公告",
    "url": "https://zjt.xinjiang.gov.cn/xjzjt/c113382/202511/73ceece5945d44d6b465171057b37408.shtml",
    "date": "2025-10-15",
    "categories": []
  },
  {
    "source": "zjt",
    "title": "新疆维吾尔自治区建设工程招标投标服务中心拟申请注销登记的公告",
    "url": "https://zjt.xinjiang.gov.cn/xjzjt/c113382/202511/ee534208b7244b85b651863e4da04b9d.shtml",
    "date": "2025-10-15",
    "categories": []
  },
  {
    "source": "zjt",
    "title": "关于发布2025年度自治区优质工程培育典型案例项目清单的通知",
    "url": "https://zjt.xinjiang.gov.cn/xjzjt/c113382/202510/4614ba73e29f44549b5e44ee30c3daa2.shtml",
    "date": "2025-10-15",
    "categories": []
  },
  {
    "source": "zjt",
    "title": "关于施工企业2025年第三季度信用评价结果的公示",
    "url": "https://zjt.xinjiang.gov.cn/xjzjt/c113382/202510/542e46a448ae4d0c9c1d5364b8b164cd.shtml",
    "date": "2025-10-14",
    "categories": []
  },
  {
    "source": "zjt",
    "title": "关于2025年第八批《新疆维吾尔自治区新型墙体材料认定证书》的公示",
    "url": "https://zjt.xinjiang.gov.cn/xjzjt/c113382/202510/230efbe0bc894a4e967ff503ed633a59.shtml",
    "date": "2025-10-13",
    "categories": []
  },
  {
    "source": "zjt",
    "title": "关于调整自治区房地产价格评估专家委员会成员的通知",
    "url": "https://zjt.xinjiang.gov.cn/xjzjt/c113382/202510/85af5db36c7749e28d5670886dfe64bb.shtml",
    "date": "2025-10-13",
    "categories": [
      "勘误"
    ]
  },
  {
    "source": "zjt",
    "title": "于开展2025年度自治区工程建设标准复审工作的通知",
    "url": "https://zjt.xinjiang.gov.cn/xjzjt/c113382/202510/1e94352a1a00408082fbf8d16db38c81.shtml",
    "date": "2025-10-13",
    "categories": []
  },
  {
    "source": "zjt",
    "title": "《自治区城镇供热管理办法（征求意见稿）》立法听证会公告",
    "url": "https://zjt.xinjiang.gov.cn/xjzjt/c113382/202510/13dbf4381b9945ca813c457823525f84.shtml",
    "date": "2025-10-11",
    "categories": []
  },
  {
    "source": "zjt",
    "title": "城乡居民群众冬季供暖突出问题线索投诉举报电话",
    "url": "https://zjt.xinjiang.gov.cn/xjzjt/c113382/202509/b689190ef35142408334500f22b4fbff.shtml",
    "date": "2025-09-30",
    "categories": []
  },
  {
    "source": "xjzj",
    "title": "关于开展国有投资工程招标控制价（最高投标限价）数据文件上传和备查工作的通知",
    "url": "https://www.xjzj.com/Home/PoliciesDetail/4928",
    "id": "4928",
    "categories": []
  },
  {
    "source": "xjzj",
    "title": "本网站计划于6月28日至7月2日进行网络改造，请各有关单位提前下载备用文件。",
    "url": "https://www.xjzj.com/Home/PoliciesDetail/4859",
    "id": "4859",
    "categories": []
  },
  {
    "source": "xjzj",
    "title": "《关于在房屋建筑和市政基础设施工程中推行施工过程结算的实施意见（征求意见稿）》公开征求意见的通知",
    "url": "https://www.xjzj.com/Home/PoliciesDetail/4783",
    "id": "4783",
    "categories": []
  },
  {
    "source": "xjzj",
    "title": "自治区住房和城乡建设厅传达学习贯彻自治区两会精神",
    "url": "https://www.xjzj.com/Home/PoliciesDetail/5049",
    "id": "5049",
    "categories": []
  },
  {
    "source": "xjzj",
    "title": "造价总站党支部开展“学纪、知纪、明纪、守纪”党日活动",
    "url": "https://www.xjzj.com/Home/PoliciesDetail/6264",
    "id": "6264",
    "categories": []
  },
  {
    "source": "xjzj",
    "title": "自治区住房和城乡建设厅召开党组（扩大）会议传达学习党的二十届三中全会精神",
    "url": "https://www.xjzj.com/Home/PoliciesDetail/6317",
    "id": "6317",
    "categories": []
  },
  {
    "source": "xjzj",
    "title": "造价总站党支部开展“弘扬伟大建党精神”主题党日活动",
    "url": "https://www.xjzj.com/Home/PoliciesDetail/6310",
    "id": "6310",
    "categories": []
  },
  {
    "source": "xjzj",
    "title": "新疆维吾尔自治区建筑业高质量发展专题培训班在武汉市成功举办",
    "url": "https://www.xjzj.com/Home/PoliciesDetail/6437",
    "id": "6437",
    "categories": []
  },
  {
    "source": "xjzj",
    "title": "伊犁州直各县市2026年4月份建设工程综合价格信息",
    "url": "https://www.xjzj.com/Home/PoliciesDetail/6790",
    "id": "6790",
    "categories": [
      "材料信息价"
    ]
  },
  {
    "source": "xjzj",
    "title": "五家渠市2026年4月建设工程综合价格信息",
    "url": "https://www.xjzj.com/Home/PoliciesDetail/6789",
    "id": "6789",
    "categories": [
      "材料信息价"
    ]
  },
  {
    "source": "xjzj",
    "title": "乌鲁木齐市2026年4月份建设工程综合价格信息",
    "url": "https://www.xjzj.com/Home/PoliciesDetail/6788",
    "id": "6788",
    "categories": [
      "材料信息价"
    ]
  },
  {
    "source": "xjzj",
    "title": "吐鲁番2026年4月份建设工程综合价格信息",
    "url": "https://www.xjzj.com/Home/PoliciesDetail/6787",
    "id": "6787",
    "categories": [
      "材料信息价"
    ]
  },
  {
    "source": "xjzj",
    "title": "塔城地区2026年4月份建设工程综合价格信息",
    "url": "https://www.xjzj.com/Home/PoliciesDetail/6786",
    "id": "6786",
    "categories": [
      "材料信息价"
    ]
  },
  {
    "source": "xjzj",
    "title": "石河子地区2026年4月份建设工程综合价格信息",
    "url": "https://www.xjzj.com/Home/PoliciesDetail/6785",
    "id": "6785",
    "categories": [
      "材料信息价"
    ]
  },
  {
    "source": "xjzj",
    "title": "克州2026年4月份建设工程综合价格信息",
    "url": "https://www.xjzj.com/Home/PoliciesDetail/6784",
    "id": "6784",
    "categories": [
      "材料信息价"
    ]
  },
  {
    "source": "xjzj",
    "title": "住房城乡建设部召开智能建造工作现场会",
    "url": "https://www.xjzj.com/Home/PoliciesDetail/6431",
    "id": "6431",
    "categories": [
      "智能建造"
    ]
  },
  {
    "source": "xjzj",
    "title": "住建部部长倪虹在国新办新闻发布会上介绍住房城乡建设...",
    "url": "https://www.xjzj.com/Home/PoliciesDetail/6383",
    "id": "6383",
    "categories": []
  },
  {
    "source": "xjzj",
    "title": "住建部赴乌鲁木齐市调研智能建造试点工作",
    "url": "https://www.xjzj.com/Home/PoliciesDetail/6382",
    "id": "6382",
    "categories": [
      "智能建造"
    ]
  },
  {
    "source": "xjzj",
    "title": "“总对总”协同推进住房城乡建设领域民事纠纷化解 住...",
    "url": "https://www.xjzj.com/Home/PoliciesDetail/6384",
    "id": "6384",
    "categories": []
  },
  {
    "source": "xjzj",
    "title": "李克强主持召开国务院常务会议  部署做好大宗商品保...",
    "url": "https://www.xjzj.com/Home/PoliciesDetail/4332",
    "id": "4332",
    "categories": []
  },
  {
    "source": "xjzj",
    "title": "自治区住房和城乡建设厅举办推进城市高质量发展暨新型...",
    "url": "https://www.xjzj.com/Home/PoliciesDetail/6433",
    "id": "6433",
    "categories": []
  },
  {
    "source": "xjzj",
    "title": "关于印发《自治区关于新冠病毒感染疫情防控期间房屋建...",
    "url": "https://www.xjzj.com/Home/PoliciesDetail/4704",
    "id": "4704",
    "categories": []
  },
  {
    "source": "xjzj",
    "title": "关于发布《新疆维吾尔自治区房屋建筑与装饰工程消耗量...",
    "url": "https://www.xjzj.com/Home/PoliciesDetail/4098",
    "id": "4098",
    "categories": []
  },
  {
    "source": "xjzj",
    "title": "关于应对新冠肺炎疫情影响 做好我区建设工程计价有关...",
    "url": "https://www.xjzj.com/Home/PoliciesDetail/4058",
    "id": "4058",
    "categories": []
  },
  {
    "source": "xjzj",
    "title": "关于征求《新疆维吾尔自治区安装工程补充消耗量定额（...",
    "url": "https://www.xjzj.com/Home/PoliciesDetail/4051",
    "id": "4051",
    "categories": [
      "定额"
    ]
  },
  {
    "source": "xjzj",
    "title": "新疆维吾尔自治区各地（州、市）造价站联系方式",
    "url": "https://www.xjzj.com/Home/PoliciesDetail/6407",
    "id": "6407",
    "categories": []
  },
  {
    "source": "xjzj",
    "title": "新疆维吾尔自治区建筑业发展中心职责",
    "url": "https://www.xjzj.com/Home/PoliciesDetail/6406",
    "id": "6406",
    "categories": []
  },
  {
    "source": "xjzj",
    "title": "价格信息浏览下载快速通道",
    "url": "https://www.xjzj.com/Home/PoliciesDetail/3595",
    "id": "3595",
    "categories": []
  },
  {
    "source": "xjzj",
    "title": "自治区各地、州、市2026年4月建设工程...",
    "url": "https://www.xjzj.com/Home/PoliciesDetail/6773",
    "id": "6773",
    "categories": []
  },
  {
    "source": "xjzj",
    "title": "自治区各地、州、市2026年3月份建设工...",
    "url": "https://www.xjzj.com/Home/PoliciesDetail/6754",
    "id": "6754",
    "categories": []
  },
  {
    "source": "xjzj",
    "title": "自治区各地、州、市2025年2月份建设工...",
    "url": "https://www.xjzj.com/Home/PoliciesDetail/6734",
    "id": "6734",
    "categories": []
  },
  {
    "source": "xjzj",
    "title": "自治区各地、州、市2026年1月份建设工...",
    "url": "https://www.xjzj.com/Home/PoliciesDetail/6716",
    "id": "6716",
    "categories": []
  },
  {
    "source": "xjzj",
    "title": "自治区各地、州、市2025年12月份建设...",
    "url": "https://www.xjzj.com/Home/PoliciesDetail/6696",
    "id": "6696",
    "categories": []
  },
  {
    "source": "xjzj",
    "title": "关于发布《新疆维吾尔自治区智能建造 （建...",
    "url": "https://www.xjzj.com/Home/PoliciesDetail/6772",
    "id": "6772",
    "categories": [
      "智能建造"
    ]
  },
  {
    "source": "xjzj",
    "title": "关于贯彻执行《建设工程工程量清单计价标准...",
    "url": "https://www.xjzj.com/Home/PoliciesDetail/6753",
    "id": "6753",
    "categories": [
      "国标"
    ]
  },
  {
    "source": "xjzj",
    "title": "关于《新疆维吾尔自治区建设工程造价管理办...",
    "url": "https://www.xjzj.com/Home/PoliciesDetail/6752",
    "id": "6752",
    "categories": [
      "造价管理办法"
    ]
  },
  {
    "source": "xjzj",
    "title": "关于面向全社会公开征求《新疆维吾尔自治区...",
    "url": "https://www.xjzj.com/Home/PoliciesDetail/6694",
    "id": "6694",
    "categories": []
  },
  {
    "source": "xjzj",
    "title": "关于《智能建造（建筑机器人）消耗量定额项...",
    "url": "https://www.xjzj.com/Home/PoliciesDetail/6657",
    "id": "6657",
    "categories": [
      "定额",
      "智能建造"
    ]
  },
  {
    "source": "xjzj",
    "title": "全过程工程咨询专题培训班在安徽合肥成功举...",
    "url": "https://www.xjzj.com/Home/PoliciesDetail/6432",
    "id": "6432",
    "categories": []
  },
  {
    "source": "xjzj",
    "title": "关于开展2013年度全区建设工程造价员资...",
    "url": "https://www.xjzj.com/Home/PoliciesDetail/1669",
    "id": "1669",
    "categories": []
  },
  {
    "source": "xjzj",
    "title": "关于公布2013年度全国建设工程造价员初...",
    "url": "https://www.xjzj.com/Home/PoliciesDetail/1663",
    "id": "1663",
    "categories": []
  },
  {
    "source": "xjzj",
    "title": "关于举办2013年度全国建设工程造价员初...",
    "url": "https://www.xjzj.com/Home/PoliciesDetail/1658",
    "id": "1658",
    "categories": []
  },
  {
    "source": "xjzj",
    "title": "关于开展我区2013年度全国建设工程造价...",
    "url": "https://www.xjzj.com/Home/PoliciesDetail/1655",
    "id": "1655",
    "categories": []
  },
  {
    "source": "xjzj",
    "title": "住房城乡建设部关于印发《城市数字公共基础...",
    "url": "https://www.xjzj.com/Home/PoliciesDetail/6428",
    "id": "6428",
    "categories": []
  },
  {
    "source": "xjzj",
    "title": "“数字住建”建设整体布局规划",
    "url": "https://www.xjzj.com/Home/PoliciesDetail/6429",
    "id": "6429",
    "categories": []
  },
  {
    "source": "xjzj",
    "title": "国家发展改革委重大项目后评价管理办法",
    "url": "https://www.xjzj.com/Home/PoliciesDetail/6369",
    "id": "6369",
    "categories": []
  },
  {
    "source": "xjzj",
    "title": "住房城乡建设部办公厅　人力资源社会保障部...",
    "url": "https://www.xjzj.com/Home/PoliciesDetail/6430",
    "id": "6430",
    "categories": []
  },
  {
    "source": "xjzj",
    "title": "中华人民共和国公司法",
    "url": "https://www.xjzj.com/Home/PoliciesDetail/6354",
    "id": "6354",
    "categories": []
  },
  {
    "source": "xjzj",
    "title": "关于印发《自治区工程造价改革实施方案》的...",
    "url": "https://www.xjzj.com/Home/PoliciesDetail/6538",
    "id": "6538",
    "categories": []
  },
  {
    "source": "xjzj",
    "title": "关于印发《自治区房屋建筑和市政基础设施工...",
    "url": "https://www.xjzj.com/Home/PoliciesDetail/6479",
    "id": "6479",
    "categories": []
  },
  {
    "source": "xjzj",
    "title": "新疆“好房子”建设暨房地产高质量发展研讨...",
    "url": "https://www.xjzj.com/Home/PoliciesDetail/6427",
    "id": "6427",
    "categories": []
  },
  {
    "source": "xjzj",
    "title": "关于发布《严寒和寒冷地区居住建筑节能设计...",
    "url": "https://www.xjzj.com/Home/PoliciesDetail/6440",
    "id": "6440",
    "categories": []
  },
  {
    "source": "xjzj",
    "title": "关于发布《建筑吊篮安全施工管理规程》等8...",
    "url": "https://www.xjzj.com/Home/PoliciesDetail/6309",
    "id": "6309",
    "categories": []
  },
  {
    "source": "xjzj",
    "title": "关于奎屯地区实施建筑业增值税新税率调整建...",
    "url": "https://www.xjzj.com/Home/PoliciesDetail/3314",
    "id": "3314",
    "categories": [
      "勘误"
    ]
  },
  {
    "source": "xjzj",
    "title": "昌吉州住房和城乡建设局转发自治区住房和城...",
    "url": "https://www.xjzj.com/Home/PoliciesDetail/3308",
    "id": "3308",
    "categories": []
  },
  {
    "source": "xjzj",
    "title": "关于印发《乌鲁木齐市建筑市场主体信用评价...",
    "url": "https://www.xjzj.com/Home/PoliciesDetail/1467",
    "id": "1467",
    "categories": []
  },
  {
    "source": "xjzj",
    "title": "关于禁止在施工现场搅拌砂浆的通知",
    "url": "https://www.xjzj.com/Home/PoliciesDetail/1465",
    "id": "1465",
    "categories": []
  },
  {
    "source": "xjzj",
    "title": "关于进一步加强建筑工程钢筋质量监督管理工...",
    "url": "https://www.xjzj.com/Home/PoliciesDetail/1464",
    "id": "1464",
    "categories": []
  }
]